symphony_summary/__init__.py
symphony_summary/_frontend.py
symphony_summary/_version.py
symphony_summary/widget.py
symphony_summary/labextension/build_log.json
symphony_summary/labextension/package.json
symphony_summary/labextension/static/lib_index_js.8f405c039cd6497669d3.js
symphony_summary/labextension/static/lib_index_js.8f405c039cd6497669d3.js.map
symphony_summary/labextension/static/lib_index_js.be75ebb739b45f956a38.js
symphony_summary/labextension/static/lib_index_js.be75ebb739b45f956a38.js.map
symphony_summary/labextension/static/remoteEntry.9eb0417750bb305c977e.js
symphony_summary/labextension/static/remoteEntry.9eb0417750bb305c977e.js.map
symphony_summary/labextension/static/remoteEntry.ae36f72436f60494d4ea.js
symphony_summary/labextension/static/remoteEntry.ae36f72436f60494d4ea.js.map
symphony_summary/labextension/static/style.js
symphony_summary/nbextension/extension.js
symphony_summary/nbextension/index.js
symphony_summary/standalone/widgets/SymphonySummary.js
symphony_summary/standalone/widgets/SymphonySummary.js.map
symphony_summary-1.0.2.data/data/etc/jupyter/nbconfig/notebook.d/symphony_summary.json
symphony_summary-1.0.2.data/data/share/jupyter/labextensions/symphony-summary/build_log.json
symphony_summary-1.0.2.data/data/share/jupyter/labextensions/symphony-summary/install.json
symphony_summary-1.0.2.data/data/share/jupyter/labextensions/symphony-summary/package.json
symphony_summary-1.0.2.data/data/share/jupyter/labextensions/symphony-summary/static/lib_index_js.be75ebb739b45f956a38.js
symphony_summary-1.0.2.data/data/share/jupyter/labextensions/symphony-summary/static/lib_index_js.be75ebb739b45f956a38.js.map
symphony_summary-1.0.2.data/data/share/jupyter/labextensions/symphony-summary/static/remoteEntry.ae36f72436f60494d4ea.js
symphony_summary-1.0.2.data/data/share/jupyter/labextensions/symphony-summary/static/remoteEntry.ae36f72436f60494d4ea.js.map
symphony_summary-1.0.2.data/data/share/jupyter/labextensions/symphony-summary/static/style.js
symphony_summary-1.0.2.dist-info/LICENSE.txt
symphony_summary-1.0.2.dist-info/METADATA
symphony_summary-1.0.2.dist-info/WHEEL
symphony_summary-1.0.2.dist-info/top_level.txt
symphony_summary-1.0.2.dist-info/RECORD
